marketdata/__init__.py
marketdata/client.py
marketdata/client_async.py
marketdata/client_params.py
marketdata/credentials.py
marketdata/manager.py
marketdata_py-0.0.6.dist-info/LICENSE
marketdata_py-0.0.6.dist-info/METADATA
marketdata_py-0.0.6.dist-info/WHEEL
marketdata_py-0.0.6.dist-info/top_level.txt
marketdata_py-0.0.6.dist-info/RECORD
