Metadata-Version: 2.1
Name: marketdata-py
Version: 0.0.6
Summary: A Python client for the marketdata.app API
Author-email: Michael Ploof <michael@tinkertech.io>
Classifier: Development Status :: 3 - Alpha
Classifier: Intended Audience :: Developers
Classifier: License :: OSI Approved :: GNU General Public License v3 (GPLv3)
Classifier: Programming Language :: Python :: 3
Classifier: Programming Language :: Python :: 3.7
Classifier: Programming Language :: Python :: 3.8
Classifier: Programming Language :: Python :: 3.9
Requires-Python: >=3.7
License-File: LICENSE
Requires-Dist: requests>=2.32.3
Requires-Dist: aiohttp>=3.11.10
Requires-Dist: aiofiles>=24.1.0
Requires-Dist: pandas>=2.2.3
Requires-Dist: numpy>=2.2.0
Requires-Dist: loguru>=0.7.3
Requires-Dist: python-dateutil>=2.9.0
Requires-Dist: typing-extensions>=4.12.2
Provides-Extra: dev
Requires-Dist: pytest>=8.3.4; extra == "dev"
Requires-Dist: pytest-asyncio>=0.24.0; extra == "dev"
Requires-Dist: pytest-cov>=6.0.0; extra == "dev"
Requires-Dist: pytest-mock>=3.14.0; extra == "dev"
Requires-Dist: black>=24.10.0; extra == "dev"
Requires-Dist: isort>=5.13.2; extra == "dev"
Requires-Dist: flake8>=7.1.1; extra == "dev"
Requires-Dist: mypy>=1.13.0; extra == "dev"
Requires-Dist: pre-commit>=4.0.1; extra == "dev"
Requires-Dist: sphinx>=8.1.3; extra == "dev"
